ml4qc/__init__.py
ml4qc/surveyml.py
ml4qc/surveymlclassifier.py
ml4qc-0.1.10.dist-info/LICENSE
ml4qc-0.1.10.dist-info/METADATA
ml4qc-0.1.10.dist-info/WHEEL
ml4qc-0.1.10.dist-info/top_level.txt
ml4qc-0.1.10.dist-info/RECORD
