Metadata-Version: 2.1
Name: ml4qc
Version: 0.1.10
Summary: Toolkit for ML-based survey quality control
Home-page: https://github.com/orangechairlabs/ml4qc
Author: Christopher Robert
Author-email: crobert@orangechairlabs.com
License: Apache 2.0
Project-URL: Documentation, https://ml4qc.readthedocs.io/
Requires-Python: >=3.7
License-File: LICENSE
Requires-Dist: pandas
Requires-Dist: numpy
Requires-Dist: scikit-learn
Requires-Dist: seaborn
Requires-Dist: matplotlib
Requires-Dist: tensorflow
Requires-Dist: importlib-metadata
Requires-Dist: k-means-constrained
